expiring_object
