Metadata-Version: 1.1
Name: expiring-object
Version: 0.0.1a3
Summary: Provides making self-removal objects
Home-page: https://github.com/sakost/expiring_object
Author: sakost
Author-email: sakost01+expiring_object@gmail.com
License: MIT
Keywords: expiring object self-removal
Platform: UNKNOWN
Classifier: Development Status :: 3 - Alpha
Classifier: License :: OSI Approved :: MIT License
Classifier: Operating System :: OS Independent
Classifier: Programming Language :: Python :: 2.6
Classifier: Programming Language :: Python :: 2.7
Classifier: Programming Language :: Python :: 3.3
Classifier: Programming Language :: Python :: 3.4
Classifier: Programming Language :: Python :: 3.5
Classifier: Programming Language :: Python :: 3.6
Classifier: Programming Language :: Python :: 3.7
Classifier: Topic :: Software Development :: Libraries :: Python Modules
